data_analytics_core/__init__.py
data_analytics_core/aws/__init__.py
data_analytics_core/aws/aws_base.py
data_analytics_core/aws/batch.py
data_analytics_core/aws/cf.py
data_analytics_core/aws/glue.py
data_analytics_core/aws/rds.py
data_analytics_core/aws/s3.py
data_analytics_core/aws/secrets_manger.py
data_analytics_core/aws/ssm.py
data_analytics_core/benchmarking/__init__.py
data_analytics_core/benchmarking/display_usage.py
data_analytics_core/benchmarking/worker_class.py
data_analytics_core/compute_ops/__init__.py
data_analytics_core/compute_ops/concurrent_processing.py
data_analytics_core/data_morphing/__init__.py
data_analytics_core/data_morphing/string_encoding.py
data_analytics_core/data_morphing/yaml_morphers.py
data_analytics_core/exceptions/__init__.py
data_analytics_core/exceptions/da_exception_class.py
data_analytics_core/exceptions/infrastructure/__init__.py
data_analytics_core/exceptions/infrastructure/aws_infrastructure_exceptions.py
data_analytics_core/localstack/__init__.py
data_analytics_core/localstack/boto_client_moks/__init__.py
data_analytics_core/localstack/boto_client_moks/localstack_clients.py
data_analytics_core/localstack/container_manager/__init__.py
data_analytics_core/localstack/container_manager/localstack_container.py
data_analytics_core/localstack/set_up/__init__.py
data_analytics_core/localstack/set_up/config.py
data_analytics_core/localstack/set_up/context.py
data_analytics_core/localstack/set_up/event_factory.py
data_analytics_core/localstack/set_up/infrastructure.py
data_analytics_core/logger/__init__.py
data_analytics_core/logger/da_core_logger.py
data_analytics_core/metaclasses/__init__.py
data_analytics_core/metaclasses/singleton.py
data_analytics_core-1.0.31.dist-info/METADATA
data_analytics_core-1.0.31.dist-info/WHEEL
data_analytics_core-1.0.31.dist-info/top_level.txt
data_analytics_core-1.0.31.dist-info/RECORD
