Metadata-Version: 2.4
Name: data-analytics-core
Version: 1.0.31
Summary: Globally shared modules in all Data & Analytics
Author-email: Marc Vea <marc.vea@code.seat>
Project-URL: Homepage, https://pypi.org/project/data-analytics-core/
Project-URL: GitHub, https://github.com/seatcode/data-analytics-core
Classifier: Programming Language :: Python :: 3.9
Classifier: License :: OSI Approved :: GNU General Public License v3 (GPLv3)
Classifier: Operating System :: OS Independent
Classifier: Development Status :: 4 - Beta
Requires-Python: >=3.9
Requires-Dist: boto3==1.28.39
Requires-Dist: botocore==1.31.39
Requires-Dist: colorlog==6.7.0
Requires-Dist: numpy==1.26.0
Requires-Dist: pandas==2.0.0
Requires-Dist: psutil==5.9.5
Requires-Dist: Requests==2.32.4
Requires-Dist: testcontainers==3.7.1
Requires-Dist: docker==7.1.0
Requires-Dist: python-dotenv==1.0.1
Requires-Dist: pyyaml==6.0.1
Requires-Dist: ruyaml==0.91.0
Requires-Dist: sqlalchemy==2.0.29
Requires-Dist: coverage==7.6.0
Requires-Dist: dill==0.3.9
Requires-Dist: awswrangler==3.9.1
Requires-Dist: moto==5.0.20
Requires-Dist: xlsxwriter==3.2.0
Requires-Dist: openpyxl==3.1.3
Provides-Extra: test
Requires-Dist: pytest; extra == "test"
Requires-Dist: pytest-cov; extra == "test"
